ptoolbox/__init__.py
ptoolbox/airtable/__init__.py
ptoolbox/airtable/airtable.py
ptoolbox/beestar/__init__.py
ptoolbox/beestar/beestar.py
ptoolbox/brilliant/__init__.py
ptoolbox/brilliant/brilliant.py
ptoolbox/cli/__init__.py
ptoolbox/cli/ptoolbox.py
ptoolbox/codeforces/__init__.py
ptoolbox/codeforces/codeforces.py
ptoolbox/codesignal/__init__.py
ptoolbox/codesignal/codesignal.py
ptoolbox/codesignal/test.py
ptoolbox/dsa/__init__.py
ptoolbox/dsa/dsa_problem.py
ptoolbox/dsa/dsa_problem_file.py
ptoolbox/geeksforgeeks/__init__.py
ptoolbox/geeksforgeeks/geeksforgeeks.py
ptoolbox/hackerrank/__init__.py
ptoolbox/hackerrank/hackerrank.py
ptoolbox/helpers/__init__.py
ptoolbox/helpers/clog.py
ptoolbox/helpers/crandom.py
ptoolbox/helpers/dsa_helper.py
ptoolbox/helpers/misc.py
ptoolbox/iqsha/__init__.py
ptoolbox/iqsha/iqsha.py
ptoolbox/judge0/__init__.py
ptoolbox/judge0/judge0.py
ptoolbox/kattis/__init__.py
ptoolbox/kattis/kattis.py
ptoolbox/logiclike/__init__.py
ptoolbox/logiclike/logiclike.py
ptoolbox/models/__init__.py
ptoolbox/models/general_models.py
ptoolbox/models/question.py
ptoolbox/repl/__init__.py
ptoolbox/repl/repl.py
ptoolbox/ucode/__init__.py
ptoolbox/ucode/course_creator.py
ptoolbox/ucode/ucode.py
ptoolbox/vjudge/__init__.py
ptoolbox/vjudge/vjudge.py
ptoolbox-0.7.7.dist-info/LICENSE.txt
ptoolbox-0.7.7.dist-info/METADATA
ptoolbox-0.7.7.dist-info/WHEEL
ptoolbox-0.7.7.dist-info/entry_points.txt
ptoolbox-0.7.7.dist-info/top_level.txt
ptoolbox-0.7.7.dist-info/RECORD
