Metadata-Version: 2.1
Name: ptoolbox
Version: 0.7.7
Summary: Tools to work with multiple problem formats: DSA, Hackerrank, CMS, repl...
Home-page: https://gitlab.com/thucnguyen/ptoolbox
Author: Thuc Nguyen
Author-email: gthuc.nguyen@gmail.com
License: MIT
Download-URL: https://pypi.org/project/ptoolbox/
Keywords: ptoolbox,problem tools
Platform: UNKNOWN
Requires-Dist: click
Requires-Dist: requests
Requires-Dist: beautifulsoup4
Requires-Dist: tomd
Requires-Dist: jinja2
Requires-Dist: dataclasses-json
Requires-Dist: websocket-client
Requires-Dist: tabulate
